msr/__init__.py
msr/context_manager.py
msr/graph/__init__.py
msr/graph/convert.py
msr/graph/draw.py
msr/graph/embed.py
msr/graph/file_io.py
msr/graph/generate.py
msr/graph/graph.py
msr/graph/graph_lib.py
msr/log_config.py
msr/msr_batch.py
msr/msr_bounds.py
msr/msr_lookup.py
msr/msr_sdp.py
msr/reduce.py
msr/strategy_config.py
msr-0.8.2.dist-info/LICENSE
msr-0.8.2.dist-info/METADATA
msr-0.8.2.dist-info/WHEEL
msr-0.8.2.dist-info/RECORD
