Metadata-Version: 2.1
Name: msr
Version: 0.8.2
Summary: Tools to compute the minimum semidefinite rank of a simple undirected graph.
License: MIT
Author: Sam Reynolds
Author-email: sreyn@proton.me
Requires-Python: >=3.11,<4.0
Classifier: License :: OSI Approved :: MIT License
Classifier: Programming Language :: Python :: 3
Classifier: Programming Language :: Python :: 3.11
Classifier: Programming Language :: Python :: 3.12
Requires-Dist: cvxpy (>=1.3,<2.0)
Requires-Dist: matplotlib (>=3.7,<4.0)
Requires-Dist: networkx (>=3.1,<4.0)
Requires-Dist: numpy (>=1.25,<2.0)
